test_package/__init__.py
test_package/bin/__init__.py
test_package/bin/cmdt.py
test_package/t_package/__init__.py
test_package/t_package/print.py
test_package1/__init__.py
test_package1/test.py
swz_test_package_v3-1.0.22.dist-info/LICENSE
swz_test_package_v3-1.0.22.dist-info/METADATA
swz_test_package_v3-1.0.22.dist-info/WHEEL
swz_test_package_v3-1.0.22.dist-info/entry_points.txt
swz_test_package_v3-1.0.22.dist-info/top_level.txt
swz_test_package_v3-1.0.22.dist-info/RECORD
